LICENSE
MANIFEST.in
README.rst
setup.cfg
setup.py
popy/__init__.py
popy/message_entry.py
popy/po_exceptions.py
popy/po_file.py
popy.egg-info/PKG-INFO
popy.egg-info/SOURCES.txt
popy.egg-info/dependency_links.txt
popy.egg-info/not-zip-safe
popy.egg-info/top_level.txt