Metadata-Version: 1.0
Name: popy
Version: 0.1.2
Summary: Parser for GNU Po files
Home-page: https://github.com/murataydos/popy
Author: Murat Aydos
Author-email: murataydos@yandex.com
License: GPL
Platform: UNKNOWN
